Metadata-Version: 2.1
Name: wsgenerator
Version: 1.0.0
Summary: Module for generating word search puzzles
Home-page: https://github.com/pgolo/wsgenerator
Author: Pavel Golovatenko-Abramov
Author-email: p.golovatenko@gmail.com
License: MIT
Platform: any
Classifier: Development Status :: 5 - Production/Stable
Classifier: Intended Audience :: Developers
Classifier: Topic :: Software Development :: Libraries :: Python Modules
Classifier: Programming Language :: Python :: 3.6
Classifier: License :: OSI Approved :: MIT License
Classifier: Operating System :: OS Independent
Requires-Python: >=3.6
License-File: LICENSE
